sagemath_categories-10.5.dist-info/top_level.txt
sagemath_categories-10.5.dist-info/RECORD
sagemath_categories-10.5.dist-info/METADATA
sagemath_categories-10.5.dist-info/WHEEL
sage/all__sagemath_categories.py
sage/categories/filtered_modules.py
sage/categories/dual.py
sage/categories/matrix_algebras.py
sage/categories/schemes.py
sage/categories/supercommutative_algebras.py
sage/categories/graded_algebras_with_basis.py
sage/categories/super_algebras_with_basis.py
sage/categories/rings.py
sage/categories/finite_permutation_groups.py
sage/categories/finite_complex_reflection_groups.py
sage/categories/vector_spaces.py
sage/categories/regular_crystals.py
sage/categories/complex_reflection_or_generalized_coxeter_groups.py
sage/categories/graded_hopf_algebras_with_basis.py
sage/categories/bialgebras_with_basis.py
sage/categories/finite_dimensional_semisimple_algebras_with_basis.py
sage/categories/super_modules_with_basis.py
sage/categories/finite_dimensional_algebras_with_basis.py
sage/categories/euclidean_domains.py
sage/categories/lattice_posets.py
sage/categories/graded_modules_with_basis.py
sage/categories/modules.py
sage/categories/commutative_additive_semigroups.py
sage/categories/topological_spaces.py
sage/categories/highest_weight_crystals.py
sage/categories/monoid_algebras.py
sage/categories/fields.py
sage/categories/super_lie_conformal_algebras.py
sage/categories/graphs.py
sage/categories/graded_bialgebras.py
sage/categories/l_trivial_semigroups.py
sage/categories/finite_dimensional_bialgebras_with_basis.py
sage/categories/drinfeld_modules.py
sage/categories/unique_factorization_domains.py
sage/categories/partially_ordered_monoids.py
sage/categories/finite_dimensional_coalgebras_with_basis.py
sage/categories/graded_hopf_algebras.py
sage/categories/additive_magmas.py
sage/categories/lie_algebras.py
sage/categories/finite_posets.py
sage/categories/g_sets.py
sage/categories/algebras_with_basis.py
sage/categories/coxeter_groups.py
sage/categories/finite_fields.py
sage/categories/infinite_enumerated_sets.py
sage/categories/loop_crystals.py
sage/categories/gcd_domains.py
